shadowfax_flash/__init__.py
shadowfax_flash/client.py
shadowfax_flash/models.py
shadowfax_flash-1.0.6.dist-info/licenses/LICENSE
shadowfax_flash-1.0.6.dist-info/METADATA
shadowfax_flash-1.0.6.dist-info/WHEEL
shadowfax_flash-1.0.6.dist-info/top_level.txt
shadowfax_flash-1.0.6.dist-info/RECORD
