Metadata-Version: 2.4
Name: shadowfax-flash
Version: 1.0.6
Summary: Async Python client for Shadowfax Flash Integration API
Author-email: Goutham Soratoor <grsoratoor@gmail.com>
Project-URL: Homepage, https://github.com/grsoratoor/shadowfax-flash
Project-URL: Bug Tracker, https://github.com/grsoratoor/shadowfax-flash/issues
Classifier: Programming Language :: Python :: 3
Classifier: License :: OSI Approved :: MIT License
Classifier: Operating System :: OS Independent
Requires-Python: >=3.11
License-File: LICENSE
Requires-Dist: httpx>=0.25.0
Requires-Dist: pydantic>=2.0.0
Requires-Dist: python-dotenv>=0.19.0
Provides-Extra: dev
Requires-Dist: pytest>=7.0.0; extra == "dev"
Requires-Dist: pytest-asyncio>=0.20.0; extra == "dev"
Requires-Dist: pytest-cov>=4.0.0; extra == "dev"
Requires-Dist: pytest-mock>=3.10.0; extra == "dev"
Requires-Dist: pytest-httpx>=0.25.0; extra == "dev"
Requires-Dist: black>=22.0.0; extra == "dev"
Requires-Dist: isort>=5.0.0; extra == "dev"
Requires-Dist: mypy>=0.990; extra == "dev"
Dynamic: license-file
